pygustus/__init__.py
pygustus/aug_comparator.py
pygustus/aug_out_filter.py
pygustus/augustus.py
pygustus/config.json
pygustus/etraining.py
pygustus/fasta_methods.py
pygustus/gff_methods.py
pygustus/util.py
pygustus/options/__init__.py
pygustus/options/aug_options.py
pygustus/options/constant.py
pygustus/options/parameters.json
pygustus/options/parameters.py
tests/__init__.py
tests/test_augustus.py
tests/test_etraining.py
pygustus-0.8.3.dist-info/LICENSE
pygustus-0.8.3.dist-info/METADATA
pygustus-0.8.3.dist-info/WHEEL
pygustus-0.8.3.dist-info/top_level.txt
pygustus-0.8.3.dist-info/RECORD
