Metadata-Version: 2.1
Name: pygustus
Version: 0.8.3
Summary: Python wrapper for AUGUSTUS.
Home-page: https://github.com/Gaius-Augustus/pygustus
Author: Daniel Honsel
Author-email: dhonsel@cs.uni.goettingen.de
License: UNKNOWN
Download-URL: https://github.com/Gaius-Augustus/pygustus/zipball/master
Platform: UNKNOWN
Classifier: Programming Language :: Python :: 3
Classifier: Development Status :: 3 - Alpha
Classifier: Environment :: Console
Classifier: Intended Audience :: Science/Research
Classifier: License :: OSI Approved :: Apache Software License
Classifier: Operating System :: POSIX :: Linux
Classifier: Topic :: Scientific/Engineering :: Bio-Informatics
